{
  "project_info": {
    "project_number": "465047772581",
    "project_id": "quizmaster-db498",
    "storage_bucket": "quizmaster-db498.appspot.com"
  },
  "client": [
    {
      "client_info": {
        "mobilesdk_app_id": "1:465047772581:android:bf2fe5ccac3af30cb85c4c",
        "android_client_info": {
          "package_name": "com.example.quizmaster"
        }
      },
      "oauth_client": [
        {
          "client_id": "465047772581-eeapnec9q66hmhuqjmacok3n50gavmsh.apps.googleusercontent.com",
          "client_type": 3
        }
      ],
      "api_key": [
        {
          "current_key": "AIzaSyBE87sF04aOSBaSs0I7u2yGjlaqD7s8xXE"
        }
      ],
      "services": {
        "appinvite_service": {
          "other_platform_oauth_client": [
            {
              "client_id": "465047772581-eeapnec9q66hmhuqjmacok3n50gavmsh.apps.googleusercontent.com",
              "client_type": 3
            }
          ]
        }
      }
    }
  ],
  "configuration_version": "1"
}